gerrit_to_platform/__init__.py
gerrit_to_platform/change_merged.py
gerrit_to_platform/comment_added.py
gerrit_to_platform/config.py
gerrit_to_platform/github.py
gerrit_to_platform/helpers.py
gerrit_to_platform/patchset_created.py
gerrit_to_platform-0.3.0.dist-info/licenses/AUTHORS.rst
gerrit_to_platform-0.3.0.dist-info/licenses/LICENSE.txt
gerrit_to_platform-0.3.0.dist-info/METADATA
gerrit_to_platform-0.3.0.dist-info/WHEEL
gerrit_to_platform-0.3.0.dist-info/entry_points.txt
gerrit_to_platform-0.3.0.dist-info/top_level.txt
gerrit_to_platform-0.3.0.dist-info/RECORD
