Metadata-Version: 2.4
Name: gerrit-to-platform
Version: 0.3.0
Summary: Gerrit to GitHub / GitLab
Author-email: Andrew Grimberg <agrimberg@linuxfoundation.org>
Maintainer-email: Andrew Grimberg <agrimberg@linuxfoundation.org>
License:                                  Apache License
Project-URL: homepage, https://gerrit.linuxfoundation.org/infra/releng/gerrit_to_platform
Project-URL: documentation, https://docs.releng.linuxfoundation.org
Project-URL: repository, https://gerrit.linuxfoundation.org/infra/releng/gerrit_to_platform
Platform: linux
Classifier: Development Status :: 4 - Beta
Classifier: Environment :: Console
Classifier: Environment :: Console :: Curses
Classifier: Intended Audience :: Developers
Classifier: Intended Audience :: System Administrators
Classifier: License :: OSI Approved :: Apache Software License
Classifier: Natural Language :: English
Classifier: Operating System :: POSIX :: Linux
Classifier: Programming Language :: Python
Classifier: Programming Language :: Python :: 3.11
Classifier: Programming Language :: Python :: 3.12
Classifier: Topic :: Software Development :: Build Tools
Classifier: Topic :: Software Development :: Quality Assurance
Classifier: Topic :: Software Development :: Testing
Classifier: Topic :: Software Development :: Version Control :: Git
Requires-Python: >=3.11
License-File: LICENSE.txt
License-File: AUTHORS.rst
Requires-Dist: ghapi~=1.0.3
Requires-Dist: typer[all]~=0.15.0
Requires-Dist: xdg~=5.1.1
Provides-Extra: testing
Requires-Dist: setuptools; extra == "testing"
Requires-Dist: pytest; extra == "testing"
Requires-Dist: pytest-cov; extra == "testing"
Requires-Dist: pytest-mock; extra == "testing"
Provides-Extra: dev
Requires-Dist: mypy; extra == "dev"
Dynamic: license-file
